<?xml version = '1.0' encoding = 'UTF-8'?>
<TableProxyOraclev12c class="oracle.dbtools.crest.model.design.storage.oracle.v12c.TableProxyOraclev12c" name="EMP_FK" directorySegmentName="seg_0" id="DC9309D0-D97F-F1DB-BA34-5A4EE75DD25D">
<createdBy>it</createdBy>
<createdTime>2025-02-14 01:47:52 UTC</createdTime>
<ownerDesignName>1</ownerDesignName>
<schemaObject>3D942C4F-D8B7-67C6-8034-A601D638D2E3</schemaObject>
<logging>YES</logging>
<partitionedRowMovement>DISABLE</partitionedRowMovement>
<segment>E1F276F4-A931-C3B5-913E-18E40B1C3D15</segment>
<tableSpace>D6D4C089-BB2B-A224-554B-2A07C5DA4342</tableSpace>
<temporaryChanged>false</temporaryChanged>
<accessDriverType>oracle_loader</accessDriverType>
<rejectLimit></rejectLimit>
<inMemory>NO</inMemory>
<columnProxies itemClass="oracle.dbtools.crest.model.design.storage.oracle.v12c.ColumnProxyOraclev12c">
<ColumnProxy name="ENAME" id="01AA816A-AE11-1F85-3297-9FAC150BE777">
<createdBy>it</createdBy>
<createdTime>2025-02-14 01:47:52 UTC</createdTime>
<ownerDesignName>1</ownerDesignName>
</ColumnProxy>
<ColumnProxy name="JOB" id="85E9A1C2-3901-43C4-47B1-27B6B480D05F">
<createdBy>it</createdBy>
<createdTime>2025-02-14 01:47:52 UTC</createdTime>
<ownerDesignName>1</ownerDesignName>
</ColumnProxy>
<ColumnProxy name="DEPTNO" id="949D4D4E-3072-0EF4-3B9F-DF1B0E0E25ED">
<createdBy>it</createdBy>
<createdTime>2025-02-14 01:47:52 UTC</createdTime>
<ownerDesignName>1</ownerDesignName>
</ColumnProxy>
<ColumnProxy name="EMPNO" id="D1A655CE-448C-EADE-504F-7142821B0CB0">
<createdBy>it</createdBy>
<createdTime>2025-02-14 01:47:52 UTC</createdTime>
<ownerDesignName>1</ownerDesignName>
</ColumnProxy>
</columnProxies>
<indexProxies>
<IndexProxy class="oracle.dbtools.crest.model.design.storage.oracle.v10g.IndexProxyOraclev10g" name="EMP_FK_EMPNO_PK" id="2C16AEE2-B2D8-1CF6-4985-1E72D0FD4BCD">
<createdBy>it</createdBy>
<createdTime>2025-02-14 01:47:52 UTC</createdTime>
<ownerDesignName>1</ownerDesignName>
<schemaObject>3D942C4F-D8B7-67C6-8034-A601D638D2E3</schemaObject>
<segment>7C4A2957-2D0F-C0A4-7899-498D3A1B7A4B</segment>
<tableSpace>D6D4C089-BB2B-A224-554B-2A07C5DA4342</tableSpace>
</IndexProxy>
</indexProxies>
<primaryKeys>
<PrimaryKey class="oracle.dbtools.crest.model.design.storage.oracle.v10g.PKProxyOraclev10g" name="EMP_FK_EMPNO_PK" id="7D873918-C3D6-DF07-FE55-8A4A8E55B662">
<createdBy>it</createdBy>
<createdTime>2025-02-14 01:47:52 UTC</createdTime>
<ownerDesignName>1</ownerDesignName>
<segment>7C4A2957-2D0F-C0A4-7899-498D3A1B7A4B</segment>
<tableSpace>D6D4C089-BB2B-A224-554B-2A07C5DA4342</tableSpace>
<existingIndex>2C16AEE2-B2D8-1CF6-4985-1E72D0FD4BCD</existingIndex>
<indexSegment>7C4A2957-2D0F-C0A4-7899-498D3A1B7A4B</indexSegment>
<indexSort>SORTED</indexSort>
<usingIndex>BY INDEX NAME</usingIndex>
</PrimaryKey>
</primaryKeys>
</TableProxyOraclev12c>